setup.py
sets/__init__.py
sets/utility.py
sets.egg-info/PKG-INFO
sets.egg-info/SOURCES.txt
sets.egg-info/dependency_links.txt
sets.egg-info/requires.txt
sets.egg-info/top_level.txt
sets/core/__init__.py
sets/core/dataset.py
sets/core/embedding.py
sets/core/step.py
sets/dataset/__init__.py
sets/dataset/mnist.py
sets/dataset/ocr.py
sets/dataset/semeval.py
sets/process/__init__.py
sets/process/concat.py
sets/process/glove.py
sets/process/normalize.py
sets/process/onehot.py
sets/process/split.py
sets/process/tokenize.py
sets/process/word_distance.py
test/test_cache.py
test/test_core.py
test/test_dataset.py
test/test_utility.py