Metadata-Version: 1.0
Name: sets
Version: 0.3.1
Summary: Read datasets in a standard way.
Home-page: http://github.com/danijar/sets
Author: Danijar Hafner
Author-email: mail@danijar.com
License: MIT
Platform: UNKNOWN
